LICENSE
MANIFEST.in
README.rst
setup.py
associations/__init__.py
associations/admin.py
associations/bootstraputils.py
associations/models.py
associations/tests.py
associations/urls.py
associations/utils.py
associations/views.py
associations/static/.DS_Store
associations/static/css/font-awesome.min.css
associations/static/css/pure-min.css
associations/static/css/layouts/overrides.css
associations/static/css/layouts/side-menu.css
associations/static/fonts/FontAwesome.otf
associations/static/fonts/fontawesome-webfont.eot
associations/static/fonts/fontawesome-webfont.svg
associations/static/fonts/fontawesome-webfont.ttf
associations/static/fonts/fontawesome-webfont.woff
associations/static/images/associations1.png
associations/static/images/associations2.png
associations/static/js/bootstrap.js
associations/static/js/bootstrap.min.js
associations/static/js/jquery.min.js
associations/static/js/ui.js
associations/static/js/uienhancement.js
associations/templates/about.html
associations/templates/associations.html
associations/templates/list_apps.html
associations/templates/master_ass.html
associations/templates/usage.html
associations/templatetags/__init__.py
associations/templatetags/__init__.pyc
associations/templatetags/detailed_tags.py
associations/templatetags/detailed_tags.pyc
django_associations.egg-info/PKG-INFO
django_associations.egg-info/SOURCES.txt
django_associations.egg-info/dependency_links.txt
django_associations.egg-info/requires.txt
django_associations.egg-info/top_level.txt